pyzzle-2024.1.4.dist-info/LICENSE
pyzzle-2024.1.4.dist-info/WHEEL
pyzzle-2024.1.4.dist-info/RECORD
pyzzle-2024.1.4.dist-info/METADATA
pyzzle/__init__.py
pyzzle/Exception.py
pyzzle/ObjectiveFunction.py
pyzzle/Word.py
pyzzle/Puzzle.py
pyzzle/Dictionary.py
pyzzle/Judgement.py
pyzzle/futils.cpython-312-x86_64-linux-musl.so
pyzzle/Placeable.py
pyzzle/Optimizer.py
pyzzle/History.py
pyzzle/Gravity.py
pyzzle/PyzzleAPI.py
pyzzle/utils.py
pyzzle/Mask.py
